odoo/addons/editorial_subscriptions/CHANGELOG.md
odoo/addons/editorial_subscriptions/Readme.md
odoo/addons/editorial_subscriptions/__init__.py
odoo/addons/editorial_subscriptions/__manifest__.py
odoo/addons/editorial_subscriptions/data/subscription_data.xml
odoo/addons/editorial_subscriptions/models/__init__.py
odoo/addons/editorial_subscriptions/models/editorial_subscription.py
odoo/addons/editorial_subscriptions/security/ir.model.access.csv
odoo/addons/editorial_subscriptions/views/add_to_subscriptions_view.xml
odoo/addons/editorial_subscriptions/views/sale_subscription_form.xml
odoo/addons/editorial_subscriptions/views/messages/product_added_to_subscriptions.xml
odoo/addons/editorial_subscriptions/wizards/__init__.py
odoo/addons/editorial_subscriptions/wizards/add_to_subscriptions_wizard.py
odoo_addon_editorial_subscriptions-17.0.1.0.2.dist-info/METADATA
odoo_addon_editorial_subscriptions-17.0.1.0.2.dist-info/WHEEL
odoo_addon_editorial_subscriptions-17.0.1.0.2.dist-info/top_level.txt
odoo_addon_editorial_subscriptions-17.0.1.0.2.dist-info/RECORD
