Metadata-Version: 2.1
Name: odoo-addon-editorial_subscriptions
Version: 17.0.1.0.2
Requires-Python: >=3.10
Requires-Dist: odoo-addon-gestion_editorial>=17.0dev,<17.1dev
Requires-Dist: odoo-addon-subscription_oca>=17.0dev,<17.1dev
Requires-Dist: odoo>=17.0a,<17.1dev
Summary: Adds book related functionalities to subscriptions module.
Home-page: https://simbiotica.coop/
License: AGPL-3
Author: =?utf-8?b?U2ltYmnDs3RpY2EgdGVjIFMuQ29vcC5NYWQu?=
Classifier: Programming Language :: Python
Classifier: Framework :: Odoo
Classifier: Framework :: Odoo :: 17.0
Classifier: License :: OSI Approved :: GNU Affero General Public License v3
